setup.py
logit/__init__.py
logit/crypt.py
logit/main.py
logit/utils.py
logit.egg-info/PKG-INFO
logit.egg-info/SOURCES.txt
logit.egg-info/dependency_links.txt
logit.egg-info/entry_points.txt
logit.egg-info/requires.txt
logit.egg-info/top_level.txt