Metadata-Version: 1.0
Name: logit
Version: 0.7.2
Summary: A private log for humans
Home-page: https://github.com/wbbradley/logit
Author: Will Bradley
Author-email: williambbradley@gmail.com
License: CC0
Platform: UNKNOWN
